rmw_dds_common/_dummy.cpython-311-x86_64-linux-gnu.so
ros_rmw_dds_common-4.0.0.data/data/include/rmw_dds_common/rmw_dds_common/context.hpp
ros_rmw_dds_common-4.0.0.data/data/include/rmw_dds_common/rmw_dds_common/gid_utils.hpp
ros_rmw_dds_common-4.0.0.data/data/include/rmw_dds_common/rmw_dds_common/graph_cache.hpp
ros_rmw_dds_common-4.0.0.data/data/include/rmw_dds_common/rmw_dds_common/qos.hpp
ros_rmw_dds_common-4.0.0.data/data/include/rmw_dds_common/rmw_dds_common/time_utils.hpp
ros_rmw_dds_common-4.0.0.data/data/include/rmw_dds_common/rmw_dds_common/visibility_control.h
ros_rmw_dds_common-4.0.0.data/data/include/rmw_dds_common/rmw_dds_common/msg/gid.h
ros_rmw_dds_common-4.0.0.data/data/include/rmw_dds_common/rmw_dds_common/msg/gid.hpp
ros_rmw_dds_common-4.0.0.data/data/include/rmw_dds_common/rmw_dds_common/msg/node_entities_info.h
ros_rmw_dds_common-4.0.0.data/data/include/rmw_dds_common/rmw_dds_common/msg/node_entities_info.hpp
ros_rmw_dds_common-4.0.0.data/data/include/rmw_dds_common/rmw_dds_common/msg/participant_entities_info.h
ros_rmw_dds_common-4.0.0.data/data/include/rmw_dds_common/rmw_dds_common/msg/participant_entities_info.hpp
ros_rmw_dds_common-4.0.0.data/data/include/rmw_dds_common/rmw_dds_common/msg/rosidl_generator_c__visibility_control.h
ros_rmw_dds_common-4.0.0.data/data/include/rmw_dds_common/rmw_dds_common/msg/rosidl_generator_cpp__visibility_control.hpp
ros_rmw_dds_common-4.0.0.data/data/include/rmw_dds_common/rmw_dds_common/msg/rosidl_typesupport_fastrtps_c__visibility_control.h
ros_rmw_dds_common-4.0.0.data/data/include/rmw_dds_common/rmw_dds_common/msg/rosidl_typesupport_fastrtps_cpp__visibility_control.h
ros_rmw_dds_common-4.0.0.data/data/include/rmw_dds_common/rmw_dds_common/msg/rosidl_typesupport_introspection_c__visibility_control.h
ros_rmw_dds_common-4.0.0.data/data/include/rmw_dds_common/rmw_dds_common/msg/detail/gid__builder.hpp
ros_rmw_dds_common-4.0.0.data/data/lib/python3.11/site-packages/rmw_dds_common-4.0.0-py3.11.egg-info/PKG-INFO
ros_rmw_dds_common-4.0.0.data/data/lib/python3.11/site-packages/rmw_dds_common-4.0.0-py3.11.egg-info/SOURCES.txt
ros_rmw_dds_common-4.0.0.data/data/lib/python3.11/site-packages/rmw_dds_common-4.0.0-py3.11.egg-info/dependency_links.txt
ros_rmw_dds_common-4.0.0.data/data/lib/python3.11/site-packages/rmw_dds_common-4.0.0-py3.11.egg-info/top_level.txt
ros_rmw_dds_common-4.0.0.dist-info/METADATA
ros_rmw_dds_common-4.0.0.dist-info/WHEEL
ros_rmw_dds_common-4.0.0.dist-info/top_level.txt
ros_rmw_dds_common-4.0.0.dist-info/RECORD
