Metadata-Version: 2.4
Name: ros-rmw-dds-common
Version: 4.0.0
Summary: ROS 2 C++ utilities package providing common APIs for DDS-based RMW implementations.
Requires-Dist: ros-rosidl-runtime-c~=4.9.5
Requires-Dist: ros-rmw-security-common~=7.8.2
Requires-Dist: ros-rcutils~=6.9.8
Requires-Dist: ros-rcpputils~=2.13.5
Requires-Dist: ros-rmw~=7.8.2
Requires-Dist: ros-rosidl-runtime-cpp~=4.9.5
Requires-Dist: ros-rosidl-default-runtime~=1.7.1
Dynamic: description
Dynamic: description-content-type
Dynamic: requires-dist
Dynamic: summary
